me_setups/__init__.py
me_setups/utils.py
me_setups/boards/__init__.py
me_setups/boards/default_boards.py
me_setups/boards/gas52.py
me_setups/boards/types.py
me_setups/components/__init__.py
me_setups/components/comp.py
me_setups/components/eqs.py
me_setups/components/mcs.py
me_setups/components/mcu.py
me_setups-1.9.1.dist-info/METADATA
me_setups-1.9.1.dist-info/WHEEL
me_setups-1.9.1.dist-info/top_level.txt
me_setups-1.9.1.dist-info/RECORD
