Metadata-Version: 2.1
Name: me-setups
Version: 1.9.1
Summary: Abstraction for Mobileye setups.
Home-page: http://gitlab.mobileye.com/idof/me-setups
Author: Ido Frenkel
Author-email: ido.frenkel@mobileye.com
Classifier: License :: OSI Approved :: MIT License
Classifier: Programming Language :: Python :: 3
Classifier: Programming Language :: Python :: 3 :: Only
Classifier: Programming Language :: Python :: Implementation :: CPython
Classifier: Programming Language :: Python :: Implementation :: PyPy
Requires-Python: >=3.7
Requires-Dist: pyserial (>=3.5)
Requires-Dist: typing-extensions (>=4.5.0) ; python_version < "3.8"
